odoo/addons/maintenance_plan/README.rst
odoo/addons/maintenance_plan/__init__.py
odoo/addons/maintenance_plan/__manifest__.py
odoo/addons/maintenance_plan/hooks.py
odoo/addons/maintenance_plan/data/ir_cron.xml
odoo/addons/maintenance_plan/demo/demo_maintenance_plan.xml
odoo/addons/maintenance_plan/i18n/es.po
odoo/addons/maintenance_plan/i18n/fr.po
odoo/addons/maintenance_plan/i18n/it.po
odoo/addons/maintenance_plan/i18n/maintenance_plan.pot
odoo/addons/maintenance_plan/i18n/pt.po
odoo/addons/maintenance_plan/i18n/zh_CN.po
odoo/addons/maintenance_plan/migrations/18.0.1.0.0/pre-migrate.py
odoo/addons/maintenance_plan/models/__init__.py
odoo/addons/maintenance_plan/models/maintenance_equipment.py
odoo/addons/maintenance_plan/models/maintenance_kind.py
odoo/addons/maintenance_plan/models/maintenance_plan.py
odoo/addons/maintenance_plan/models/maintenance_request.py
odoo/addons/maintenance_plan/models/res_config_settings.py
odoo/addons/maintenance_plan/readme/CONTEXT.md
odoo/addons/maintenance_plan/readme/CONTRIBUTORS.md
odoo/addons/maintenance_plan/readme/DESCRIPTION.md
odoo/addons/maintenance_plan/readme/INSTALL.md
odoo/addons/maintenance_plan/readme/USAGE.md
odoo/addons/maintenance_plan/security/ir.model.access.csv
odoo/addons/maintenance_plan/security/maintenance_security.xml
odoo/addons/maintenance_plan/static/description/icon.png
odoo/addons/maintenance_plan/static/description/index.html
odoo/addons/maintenance_plan/tests/__init__.py
odoo/addons/maintenance_plan/tests/common.py
odoo/addons/maintenance_plan/tests/test_maintenance_plan.py
odoo/addons/maintenance_plan/tests/test_maintenance_plan_domain.py
odoo/addons/maintenance_plan/views/maintenance_equipment_views.xml
odoo/addons/maintenance_plan/views/maintenance_kind_views.xml
odoo/addons/maintenance_plan/views/maintenance_plan_views.xml
odoo/addons/maintenance_plan/views/maintenance_request_views.xml
odoo/addons/maintenance_plan/views/report_maintenance_request.xml
odoo_addon_maintenance_plan-18.0.1.0.0.9.dist-info/METADATA
odoo_addon_maintenance_plan-18.0.1.0.0.9.dist-info/WHEEL
odoo_addon_maintenance_plan-18.0.1.0.0.9.dist-info/top_level.txt
odoo_addon_maintenance_plan-18.0.1.0.0.9.dist-info/RECORD
