Metadata-Version: 2.1
Name: odoo-addon-maintenance_plan
Version: 18.0.1.0.0.9
Requires-Python: >=3.10
Requires-Dist: odoo-addon-base_maintenance==18.0.*
Requires-Dist: odoo==18.0.*
Requires-Dist: python-dateutil
Summary: Extends preventive maintenance planning
Home-page: https://github.com/OCA/maintenance
License: AGPL-3
Author: Camptocamp SA, ForgeFlow, Odoo Community Association (OCA)
Author-email: support@odoo-community.org
Classifier: Programming Language :: Python
Classifier: Framework :: Odoo
Classifier: Framework :: Odoo :: 18.0
Classifier: License :: OSI Approved :: GNU Affero General Public License v3
